LICENSE
MANIFEST.in
README.rst
setup.py
dfapp/__init__.py
dfapp/mixins.py
dfapp/views.py
dfapp/static/dfapp/js/update_form.js
dfapp/templates/dfapp/widgets/front_select.html
django_dfapp.egg-info/PKG-INFO
django_dfapp.egg-info/SOURCES.txt
django_dfapp.egg-info/dependency_links.txt
django_dfapp.egg-info/top_level.txt